setup.py
line_ex_sar_forex_next3/__init__.py
line_ex_sar_forex_next3/line_ex_sar_forex_next3.py
line_ex_sar_forex_next3.egg-info/PKG-INFO
line_ex_sar_forex_next3.egg-info/SOURCES.txt
line_ex_sar_forex_next3.egg-info/dependency_links.txt
line_ex_sar_forex_next3.egg-info/not-zip-safe
line_ex_sar_forex_next3.egg-info/top_level.txt